tinytoken/__init__.py
tinytoken/py.typed
tinytoken_sdk-0.1.3.dist-info/METADATA
tinytoken_sdk-0.1.3.dist-info/WHEEL
tinytoken_sdk-0.1.3.dist-info/top_level.txt
tinytoken_sdk-0.1.3.dist-info/RECORD
